{"id":109801,"xmlId":"reasonml","name":"ReasonML","description":"Add support for ReasonML language. Also add support for OCaml and Dune.","tags":["Languages"],"vendor":"H.Giraud","version":"0.97-2020.3","notes":"\n                <ul>\n                    <li>#304 - Properties in component using external are not found</li>\n                    <li>Keep caret at position when reformat</li>\n                    <li>Fix file pattern introduced in bs-platform 8.3</li>\n                    <li>Fix reformatOnSave when multiple projects (different settings) are opened</li>\n                    <li>Update ErrorAnnotator to use new ninja format introduced since bs-platform 8.4</li>\n                    <li>Update ppx error extraction</li>\n                </ul>\n                <p><a href=\"https://github.com/reasonml-editor/reasonml-idea-plugin/blob/master/CHANGELOG.md\">Full change log...</a></p>\n                <p></p>\n                <p>To see how to integrate reason tools (bsc, refmt), go to the website.</p>\n            ","optionalDependencies":["com.intellij.modules.java","JavaScript"],"since":"203.0","until":"203.*","sourceCodeUrl":"https://github.com/giraud/reasonml-idea-plugin","size":1058781}